code_puppy/__init__.py
code_puppy/__main__.py
code_puppy/callbacks.py
code_puppy/chatgpt_codex_client.py
code_puppy/claude_cache_client.py
code_puppy/cli_runner.py
code_puppy/config.py
code_puppy/error_logging.py
code_puppy/gemini_code_assist.py
code_puppy/gemini_model.py
code_puppy/http_utils.py
code_puppy/keymap.py
code_puppy/main.py
code_puppy/model_factory.py
code_puppy/model_switching.py
code_puppy/model_utils.py
code_puppy/models.json
code_puppy/models_dev_api.json
code_puppy/models_dev_parser.py
code_puppy/pydantic_patches.py
code_puppy/reopenable_async_client.py
code_puppy/round_robin_model.py
code_puppy/session_storage.py
code_puppy/status_display.py
code_puppy/summarization_agent.py
code_puppy/terminal_utils.py
code_puppy/uvx_detection.py
code_puppy/version_checker.py
code_puppy/agents/__init__.py
code_puppy/agents/agent_c_reviewer.py
code_puppy/agents/agent_code_puppy.py
code_puppy/agents/agent_code_reviewer.py
code_puppy/agents/agent_cpp_reviewer.py
code_puppy/agents/agent_creator_agent.py
code_puppy/agents/agent_golang_reviewer.py
code_puppy/agents/agent_helios.py
code_puppy/agents/agent_javascript_reviewer.py
code_puppy/agents/agent_manager.py
code_puppy/agents/agent_pack_leader.py
code_puppy/agents/agent_planning.py
code_puppy/agents/agent_python_programmer.py
code_puppy/agents/agent_python_reviewer.py
code_puppy/agents/agent_qa_expert.py
code_puppy/agents/agent_qa_kitten.py
code_puppy/agents/agent_security_auditor.py
code_puppy/agents/agent_terminal_qa.py
code_puppy/agents/agent_typescript_reviewer.py
code_puppy/agents/base_agent.py
code_puppy/agents/event_stream_handler.py
code_puppy/agents/json_agent.py
code_puppy/agents/prompt_reviewer.py
code_puppy/agents/subagent_stream_handler.py
code_puppy/agents/pack/__init__.py
code_puppy/agents/pack/bloodhound.py
code_puppy/agents/pack/husky.py
code_puppy/agents/pack/retriever.py
code_puppy/agents/pack/shepherd.py
code_puppy/agents/pack/terrier.py
code_puppy/agents/pack/watchdog.py
code_puppy-0.0.384.dist-info/METADATA
code_puppy-0.0.384.dist-info/WHEEL
code_puppy-0.0.384.dist-info/entry_points.txt
code_puppy-0.0.384.dist-info/licenses/LICENSE
code_puppy-0.0.384.dist-info/RECORD
