Metadata-Version: 2.4
Name: code-puppy
Version: 0.0.384
Summary: Code generation agent
Project-URL: repository, https://github.com/mpfaffenberger/code_puppy
Project-URL: HomePage, https://github.com/mpfaffenberger/code_puppy
Author: Michael Pfaffenberger
License: MIT
License-File: LICENSE
Classifier: License :: OSI Approved :: MIT License
Classifier: Operating System :: OS Independent
Classifier: Programming Language :: Python :: 3
Classifier: Programming Language :: Python :: 3.11
Classifier: Programming Language :: Python :: 3.12
Classifier: Programming Language :: Python :: 3.13
Classifier: Topic :: Software Development :: Code Generators
Requires-Python: <3.14,>=3.11
Requires-Dist: dbos>=2.5.0
Requires-Dist: fastapi>=0.109.0
Requires-Dist: httpx[http2]>=0.24.1
Requires-Dist: json-repair>=0.46.2
Requires-Dist: mcp>=1.9.4
Requires-Dist: openai>=1.99.1
Requires-Dist: pillow>=10.0.0
Requires-Dist: playwright>=1.40.0
Requires-Dist: prompt-toolkit>=3.0.52
Requires-Dist: pydantic-ai-slim[anthropic,mcp,openai]==1.26.0
Requires-Dist: pydantic>=2.4.0
Requires-Dist: pyfiglet>=0.8.post1
Requires-Dist: python-dotenv>=1.0.0
Requires-Dist: rapidfuzz>=3.13.0
Requires-Dist: requests>=2.28.0
Requires-Dist: rich>=13.4.2
Requires-Dist: ripgrep==14.1.0
Requires-Dist: tenacity>=8.2.0
Requires-Dist: termflow-md>=0.1.8
Requires-Dist: typer>=0.12.0
Requires-Dist: uvicorn[standard]>=0.27.0
Requires-Dist: websockets>=12.0
